101Sequence/FSM101.V
module FSM101 (
    input  clk,
    input  reset_in,        // reset sincrono attivo basso
    input  in_bit,
    output seq_detected
);

    parameter S0 = 2'b00,
              S1 = 2'b01,
              S2 = 2'b10,
              S3 = 2'b11;

    reg [1:0] state, next_state;

    always @(posedge clk) begin
        if (!reset_n)
            state <= S0;
        else
            state <= next_state;
    end

    always @(*) begin
        next_state = state;
        case (state)
            S0: begin
                if (in_bit) next_state = S1;
                else        next_state = S0;
            end

            S1: begin
                if (in_bit) next_state = S1;
                else        next_state = S2;
            end

            S2: begin
                if (in_bit) next_state = S3;
                else        next_state = S0;
            end

            S3: begin
                if (in_bit) next_state = S1;
                else        next_state = S2;
            end
        endcase
    end

    assign seq_detected = (state == S3);

endmodule

101Sequence/testbench.v
`timescale 1ns/1ps
module testbench;
    reg clk;
    reg reset_in;
    reg in_bit;
    wire seq_detected;
    FSM101 uut (
        .clk(clk),
        .reset_in(reset_in),
        .in_bit(in_bit),
        .seq_detected(seq_detected)
    );
    
    always #5 clk = ~clk;

    initial begin
        $dumpfile("fsm101.vcd");
        $dumpvars(0, testbench);
        clk = 0; 
        reset_in = 0; 
        in_bit= 0;
        #10;
        reset_in = 1;
        #10; in_bit = 1;
        #10; in_bit = 0;
        #10; in_bit = 1;
        $display("Output after sequence 101: %b", seq_detected);
        #10; in_bit = 1;
        #10; in_bit = 1;
        #10; in_bit = 0;
        #10; in_bit = 0;
        #10; in_bit = 1;
        #10; in_bit = 0;
        #10; in_bit = 1;
        $display("Output after sequence 101: %b", seq_detected);
        #10; in_bit = 0;
        $finish;
     end
endmodule;

101Sequence/fsm101.vcd
$date
	Thu Jan 08 09:41:59 2026
$end
$version
	Icarus Verilog
$end
$timescale
	1ps
$end
$scope module testbench $end
$var wire 1 ! seq_detected $end
$var reg 1 " clk $end
$var reg 1 # in_bit $end
$var reg 1 $ reset_in $end
$scope module uut $end
$var wire 1 " clk $end
$var wire 1 # in_bit $end
$var wire 1 $ reset_in $end
$var wire 1 ! seq_detected $end
$var reg 2 % next_state [1:0] $end
$var reg 2 & state [1:0] $end
$upscope $end
$upscope $end
$enddefinitions $end
#0
$dumpvars
bx &
bx %
0$
0#
0"
x!
$end
#5000
b0 %
0!
b0 &
1"
#10000
0"
1$
#15000
1"
#20000
b1 %
0"
1#
#25000
b1 &
1"
#30000
b10 %
0"
0#
#35000
b0 %
b10 &
1"
#40000
b11 %
0"
1#
#45000
b1 %
1!
b11 &
1"
#50000
0"
#55000
0!
b1 &
1"
#60000
0"
#65000
1"
#70000
b10 %
0"
0#
#75000
b0 %
b10 &
1"
#80000
0"
#85000
b0 &
1"
#90000
b1 %
0"
1#
#95000
b1 &
1"
#100000
b10 %
0"
0#
#105000
b0 %
b10 &
1"
#110000
b11 %
0"
1#
#115000
b1 %
1!
b11 &
1"
#120000
b10 %
0"
0#
