mini-ALU-16bit/miniALU.v
module miniALU(
    input wire [15:0] a_i, //first operand
    input wire [15:0] b_i, //second operand
    input wire [3:0] op_i, //opcode
    input wire [3:0] shamt_i, 
    //specifica il numero di posizioni di cui spostare i bit durante le operazioni di shift 
    output reg [15:0] res_o, //result
    output reg zero_o //serve per indicare se il risultato è zero    
);

    reg [15:0] temp;
    reg sign;

    always @(*) begin 
        case (op_i)
            4'b0000: res_o = a_i + b_i; //ADD
            4'b0001: res_o = a_i - b_i; //SUB
            4'b0010: res_o = a_i & b_i; //AND
            4'b0011: res_o = a_i | b_i; //OR
            4'b0100: res_o = a_i ^ b_i; //XOR
            4'b0101: res_o = ~a_i; //NOT
            4'b0110: begin 
                temp = a_i;
                if(shamt_i[0] == 1'b1) begin 
                    temp = {temp[14:0], 1'b0}; 
                end
                if(shamt_i[1] == 1'b1) begin 
                    temp = {temp[13:0], 2'b00};
                end
                if (shamt_i[2] == 1'b1) begin 
                    temp = {temp[11:0], 4'b0000};
                end
                if (shamt_i[3] == 1'b1) begin 
                    temp = {temp[7:0], 8'b00000000};
                end
                res_o = temp; //modifichiamo temp invece che a_ direttamente, poi impostiamo l'uscita sul suo valore
            end
            4'b0111: begin 
                temp = a_i; 
                if(shamt_i[0] == 1'b1) begin 
                    temp = {1'b0, temp[15:1]};
                end
                if(shamt_i[1] == 1'b1) begin 
                    temp = {2'b00, temp[15:2]};
                end
                if(shamt_i[2] == 1'b1) begin 
                    temp = {4'b0000, temp[15:4]};
                end
                if(shamt_i[3] == 1'b1) begin 
                    temp = {8'b00000000, temp[15:8]};
                end
                res_o = temp; //modifichiamo temp invece che a_ direttamente, poi impostiamo l'uscita sul suo valore
            end
            4'b1000: begin 
                //ASR
                temp =a_i;
                sign = a_i[15];
                if(shamt_i[0] == 1'b1) begin 
                    temp = {sign, temp[15:1]};
                end
                if(shamt_i[1] == 1'b1) begin 
                    temp = { {2{sign}}, temp[15:2]}; //2{sign} è una replicazione del bit di segno
                end
                if(shamt_i[2] == 1'b1) begin 
                    temp = {{4{sign}}, temp[15:4]};
                end
                if(shamt_i[3] == 1'b1) begin 
                    temp = {{8{sign}}, temp[15:8]};
                end
                res_o=temp;
            end
            /*Lo shift a destra porta sempre ad una decrescita e a sinistra sempre ad una crescita indipendentemente dal segno*/
            default: res_o = 16'h0000;
        endcase
        zero_o = (res_o == 16'h0000);
    end

endmodule;

mini-ALU-16bit/testbench.v
module ALUtestbench;
    reg [15:0] a_i;
    reg [15:0] b_i;
    reg [3:0] op_i;
    reg [3:0] shamt_i;
    wire [15:0] res_o;
    miniALU uut (
        .a_i(a_i),
        .b_i(b_i),
        .op_i(op_i),
        .shamt_i(shamt_i),
        .res_o(res_o)
    );
    initial begin
        $dumpfile("alu_testbench.vcd");
        $dumpvars(0, ALUtestbench);
        // Test ADD
        a_i = 16'h0005; b_i = 16'h0003; op_i = 4'b0000; shamt_i = 4'b0000;
        #1; // Aspetta un ciclo
        $display("ADD: a_i=%h, b_i=%h, res_o=%h, expected=%h", a_i, b_i, res_o, 16'h0008);
        if (res_o !== 16'h0008) $display("ADD Test Failed");
        else $display("ADD Test Passed");
        #10;
        // Test SUB
        a_i = 16'h0005; b_i = 16'h0003; op_i = 4'b0001; shamt_i = 4'b0000;
        #1;
        $display("SUB: a_i=%h, b_i=%h, res_o=%h, expected=%h", a_i, b_i, res_o, 16'h0002);
        if (res_o !== 16'h0002) $display("SUB Test Failed");
        else $display("SUB Test Passed");
        #10;
        // Test AND
        a_i = 16'h00FF; b_i = 16'h0F0F; op_i = 4'b0010; shamt_i = 4'b0000;
        #1;
        $display("AND: a_i=%h, b_i=%h, res_o=%h, expected=%h", a_i, b_i, res_o, 16'h000F);
        if (res_o !== 16'h000F) $display("AND Test Failed");
        else $display("AND Test Passed");
        #10;
        // Test OR
        a_i = 16'h00FF; b_i = 16'h0F0F; op_i = 4'b0011; shamt_i = 4'b0000;
        #1;
        if (res_o !== 16'h0FFF) $display("OR Test Failed: %h | %h != %h", a_i, b_i, res_o);
        else $display("OR Test Passed: %h | %h = %h", a_i, b_i, res_o);
        #10;
        // Test XOR
        #1;
        a_i = 16'h00FF; b_i = 16'h0F0F; op_i = 4'b0100; shamt_i = 4'b0000;
        if (res_o !== 16'h0FF0) $display("XOR Test Failed: %h ^ %h != %h", a_i, b_i, res_o);
        else $display("XOR Test Passed: %h ^ %h = %h", a_i, b_i, res_o);
        #10;
        // Test NOT
        a_i = 16'h00FF; b_i = 16'h0000; op_i = 4'b0101; shamt_i = 4'b0000;
        #1;
        if (res_o !== 16'hFF00) $display("NOT Test Failed: ~%h != %h", a_i, res_o);
        else $display("NOT Test Passed: ~%h = %h", a_i, res_o);
        #10;
        // Test LSL
        a_i = 16'h0001; b_i = 16'h0000; op_i = 4'b0110; shamt_i = 4'b0011;
        #1;
        if (res_o !== 16'h0008) $display("LSL Test Failed: %h << 3 != %h", a_i, res_o);
        else $display("LSL Test Passed: %h << 3 = %h", a_i, res_o);
        #10;
        // Test LSR
        a_i = 16'h8000; b_i = 16'h0000; op_i = 4'b0111; shamt_i = 4'b0011;
        #1;
        if (res_o !== 16'h1000) $display("LSR Test Failed: %h >> 3 != %h", a_i, res_o);
        else $display("LSR Test Passed: %h >> 3 = %h", a_i, res_o);
        #10;
        // Test ASR
        a_i = 16'h8000; b_i = 16'h0000; op_i = 4'b1000; shamt_i = 4'b0011;
        #1; //ritardo artificiale per attendere che l'assegnazione avvenga
        if (res_o !== 16'hF000) $display("ASR Test Failed: %h >>> 3 != %h", a_i, res_o);
        else $display("ASR Test Passed: %h >>> 3 = %h", a_i, res_o);
        #10;
        $finish;
    end
endmodule

mini-ALU-16bit/alu_testbench.vcd
$date
	Mon Jan 12 16:54:38 2026
$end
$version
	Icarus Verilog
$end
$timescale
	1s
$end
$scope module ALUtestbench $end
$var wire 16 ! res_o [15:0] $end
$var reg 16 " a_i [15:0] $end
$var reg 16 # b_i [15:0] $end
$var reg 4 $ op_i [3:0] $end
$var reg 4 % shamt_i [3:0] $end
$scope module uut $end
$var wire 16 & a_i [15:0] $end
$var wire 16 ' b_i [15:0] $end
$var wire 4 ( op_i [3:0] $end
$var wire 4 ) shamt_i [3:0] $end
$var reg 16 * res_o [15:0] $end
$var reg 1 + sign $end
$var reg 16 , temp [15:0] $end
$var reg 1 - zero_o $end
$upscope $end
$upscope $end
$enddefinitions $end
#0
$dumpvars
0-
bx ,
x+
b1000 *
b0 )
b0 (
b11 '
b101 &
b0 %
b0 $
b11 #
b101 "
b1000 !
$end
#11
b10 !
b10 *
b1 $
b1 (
#22
b1111 !
b1111 *
b10 $
b10 (
b111100001111 #
b111100001111 '
b11111111 "
b11111111 &
#33
b111111111111 !
b111111111111 *
b11 $
b11 (
#45
b111111110000 !
b111111110000 *
b100 $
b100 (
#55
b1111111100000000 !
b1111111100000000 *
b101 $
b101 (
b0 #
b0 '
#66
b1000 !
b1000 *
b1000 ,
b11 %
b11 )
b110 $
b110 (
b1 "
b1 &
#77
b1000000000000 !
b1000000000000 *
b1000000000000 ,
b111 $
b111 (
b1000000000000000 "
b1000000000000000 &
#88
b1111000000000000 !
b1111000000000000 *
1+
b1111000000000000 ,
b1000 $
b1000 (
