registerFile/registerFile.v
module registerFile(
    input wire clk, //segnale di clock
    input wire reset, //segnale di reset, attivo basso
    input wire write_enable, //autorizzazione per la scrittura
    input wire [LOG2_NREGS-1:0] waddr_i,  //registro su cui vogliamo scrivere
    input wire [XLEN-1:0] write_data_i, //dato da scrivere nel registro
    input wire [LOG2_NREGS-1:0] read_addr1, //indirizzo da leggere 1
    output wire [XLEN-1:0] read_data1,  //dato letto dall'inidirzzo 1
    input wire [LOG2_NREGS-1:0] read_addr2,  //indirizzo da leggere 2
    output wire [XLEN-1:0] read_data2 //dato letto dall'indirizzo 2
);

parameter NREGS= 32; //numero di registri
parameter XLEN = 32; //lunghezza dei registri
parameter LOG2_NREGS = $clog2(NREGS);  //numero di bit che ci servono per rappresentare i nosri registri

integer i; //intero per l'interazione, non possiamo dichiararlo nel ciclo con iverilog
reg [XLEN-1:0] regs [0:NREGS-1]; //array per i registri 
always @(posedge clk or negedge reset) begin //aspettando il prossimo clock 
    if(reset==0) begin //se il rset è attivo resettiamo i registri 
        for(i=0; i<NREGS; i=i+1) begin 
            regs[i] <= {XLEN{1'b0}}; //scrive il valore 0 in tutti i registri
        end
    end //se è abilitata la scrittura
    else if(write_enable && waddr_i != 0)
    begin 
        regs[waddr_i] <= write_data_i; //scriviamo il dato specificato nel registro di dato 
    end
end
assign read_data1 = (read_addr1 == {LOG2_NREGS{1'b0}}) ? {XLEN{1'b0}} : regs[read_addr1]; //lettura dei due indirizzi specificati
assign read_data2 = (read_addr2 == {LOG2_NREGS{1'b0}}) ? {XLEN{1'b0}} : regs[read_addr2];

endmodule

registerFile/testbench.v
`timescale 1ns / 1ps

module testbench;

parameter NREGS = 32;
parameter XLEN = 32;
parameter LOG2_NREGS = $clog2(NREGS);

// Signals
reg clk;
reg reset;
reg write_enable;
reg [LOG2_NREGS-1:0] waddr_i;
reg [XLEN-1:0] write_data_i;
reg [LOG2_NREGS-1:0] read_addr1;
wire [XLEN-1:0] read_data1;
reg [LOG2_NREGS-1:0] read_addr2;
wire [XLEN-1:0] read_data2;

// Instantiate the register file
registerFile #(NREGS, XLEN) rf (
    .clk(clk),
    .reset(reset),
    .write_enable(write_enable),
    .waddr_i(waddr_i),
    .write_data_i(write_data_i),
    .read_addr1(read_addr1),
    .read_data1(read_data1),
    .read_addr2(read_addr2),
    .read_data2(read_data2)
);

// Clock generation
always #5 clk = ~clk;

// Test sequence
initial begin
    $dumpfile("dumpfile.vcd");
    $dumpvars(0, testbench);
    // Initialize
    clk = 0;
    reset = 0;
    write_enable = 0;
    waddr_i = 0;
    write_data_i = 0;
    read_addr1 = 0;
    read_addr2 = 0;

    // Reset
    #10 reset = 1;

    // Test writing to register 1
    #10 write_enable = 1;
    waddr_i = 1;
    write_data_i = 32'hDEADBEEF;
    #10 write_enable = 0;

    // Read register 1
    read_addr1 = 1;
    #10;
    if (read_data1 !== 32'hDEADBEEF) $display("ERROR: Register 1 read failed");

    // Test writing to register 2
    write_enable = 1;
    waddr_i = 2;
    write_data_i = 32'hCAFEBABE;
    #10 write_enable = 0;

    // Read both registers
    read_addr1 = 1;
    read_addr2 = 2;
    #10;
    if (read_data1 !== 32'hDEADBEEF) $display("ERROR: Register 1 read failed");
    if (read_data2 !== 32'hCAFEBABE) $display("ERROR: Register 2 read failed");

    // Test register 0 is always 0
    read_addr1 = 0;
    #10;
    if (read_data1 !== 0) $display("ERROR: Register 0 should be 0");

    // Test reset
    reset = 0;
    #10 reset = 1;
    read_addr1 = 1;
    #10;
    if (read_data1 !== 0) $display("ERROR: Reset failed");

    $display("Test completed");
    $finish;
end

endmodule

registerFile/dumpfile.vcd
$date
	Tue Jan 13 15:57:13 2026
$end
$version
	Icarus Verilog
$end
$timescale
	1ps
$end
$scope module testbench $end
$var wire 32 ! read_data2 [31:0] $end
$var wire 32 " read_data1 [31:0] $end
$var reg 1 # clk $end
$var reg 5 $ read_addr1 [4:0] $end
$var reg 5 % read_addr2 [4:0] $end
$var reg 1 & reset $end
$var reg 5 ' waddr_i [4:0] $end
$var reg 32 ( write_data_i [31:0] $end
$var reg 1 ) write_enable $end
$scope module rf $end
$var wire 1 # clk $end
$var wire 5 * read_addr1 [4:0] $end
$var wire 5 + read_addr2 [4:0] $end
$var wire 1 & reset $end
$var wire 5 , waddr_i [4:0] $end
$var wire 32 - write_data_i [31:0] $end
$var wire 1 ) write_enable $end
$var wire 32 . read_data2 [31:0] $end
$var wire 32 / read_data1 [31:0] $end
$var integer 32 0 i [31:0] $end
$upscope $end
$upscope $end
$enddefinitions $end
#0
$dumpvars
b100000 0
b0 /
b0 .
b0 -
b0 ,
b0 +
b0 *
0)
b0 (
b0 '
0&
b0 %
b0 $
0#
b0 "
b0 !
$end
#5000
b100000 0
1#
#10000
0#
1&
#15000
1#
#20000
0#
b11011110101011011011111011101111 (
b11011110101011011011111011101111 -
b1 '
b1 ,
1)
#25000
1#
#30000
b11011110101011011011111011101111 "
b11011110101011011011111011101111 /
0#
b1 $
b1 *
0)
#35000
1#
#40000
0#
b11001010111111101011101010111110 (
b11001010111111101011101010111110 -
b10 '
b10 ,
1)
#45000
1#
#50000
b11001010111111101011101010111110 !
b11001010111111101011101010111110 .
0#
b10 %
b10 +
0)
#55000
1#
#60000
b0 "
b0 /
0#
b0 $
b0 *
#65000
1#
#70000
b0 !
b0 .
b100000 0
0#
0&
#75000
b100000 0
1#
#80000
0#
b1 $
b1 *
1&
