Smart_traffic_controller/smart_traffic_controller.v
module smart_traffic_controller (
    /*Ci servono 3 segnali in input: clk_i (segnale di clock), 
    reset_ni (segnale di reset attivo basso), 
    carB_i (Segnale di attivazione del semaforo B)*/
    input  wire clk_i, 
    input  wire reset_ni,
    input  wire carB_i,
    output reg  A_red_o,
    output reg  A_yellow_o,
    output reg  A_green_o,
    output reg  B_red_o,
    output reg  B_yellow_o,
    output reg  B_green_o
);

    // Definizione degli stati tramite costanti locali
    localparam S_IDLE      = 2'b00; // A verde, B rosso
    localparam S_A_YELLOW  = 2'b01; // A giallo, B rosso
    localparam S_B_GREEN   = 2'b10; // A rosso, B verde
    localparam S_B_YELLOW  = 2'b11; // A rosso, B giallo

    // Registri per lo stato corrente e successivo
    reg [1:0] cs, ns;

    // Timer per contare i cicli di clock in ogni stato
    reg [1:0] timer, next_timer;

    // --- Logica sequenziale: aggiornamento stato e timer ---
    always @(posedge clk_i or negedge reset_ni) begin
        if (!reset_ni) begin
            cs <= S_IDLE;      // stato iniziale
            timer <= 2'd0;     // timer azzerato
        end else begin
            cs <= ns;          // Aggiorna stato corrente
            timer <= next_timer; // Aggiorna timer
        end
    end

    // --- Logica combinatoria: transizione degli stati ---
    always @(*) begin
        ns = cs;             // Default: rimani nello stato corrente
        next_timer = timer;  // Default: timer non cambia

        case (cs)
            S_IDLE: begin
                next_timer = 2'd0; // Azzeriamo il timer
                if (carB_i) begin
                    ns = S_A_YELLOW; // Passa ad A giallo se arriva una macchina
                end
            end

            S_A_YELLOW: begin
                if (timer == 2'd1) begin
                    ns = S_B_GREEN;   // Passa a B verde dopo 1 ciclo
                    next_timer = 2'd0; 
                end else begin
                    next_timer = timer + 2'd1; // Incrementa timer
                end
            end

            S_B_GREEN: begin
                if (timer == 2'd2) begin
                    ns = S_B_YELLOW;  // Passa a B giallo dopo 2 cicli
                    next_timer = 2'd0;
                end else begin
                    next_timer = timer + 2'd1;
                end
            end

            S_B_YELLOW: begin
                if (timer == 2'd1) begin
                    ns = S_IDLE;      // Torna allo stato iniziale
                    next_timer = 2'd0;
                end else begin
                    next_timer = timer + 2'd1;
                end
            end

            default: begin
                ns = S_IDLE;        // Default safety
                next_timer = 2'd0;
            end
        endcase
    end

    // --- Logica combinatoria: assegnazione degli output ---
    always @(*) begin
        // Default: tutti i semafori spenti
        A_red_o     = 1'b0;
        A_yellow_o  = 1'b0;
        A_green_o   = 1'b0;
        B_red_o     = 1'b0;
        B_yellow_o  = 1'b0;
        B_green_o   = 1'b0;

        case (cs)
            S_IDLE: begin
                A_green_o = 1'b1; // A verde
                B_red_o   = 1'b1; // B rosso
            end

            S_A_YELLOW: begin
                A_yellow_o = 1'b1; // A giallo
                B_red_o    = 1'b1; // B rosso
            end

            S_B_GREEN: begin
                A_red_o   = 1'b1; // A rosso
                B_green_o = 1'b1; // B verde
            end

            S_B_YELLOW: begin
                A_red_o     = 1'b1; // A rosso
                B_yellow_o  = 1'b1; // B giallo
            end
        endcase
    end

endmodule

/* SPIEGAZIONE:
- Input: clk_i (clock), reset_ni (reset attivo basso), carB_i (sensore veicolo B)
- Output: segnali per semafori A e B

1. Always sincrono: aggiorna lo stato corrente e il timer ad ogni clock, resetta se reset_ni = 0
2. Always combinatorio stato: calcola il prossimo stato e il prossimo timer in base allo stato corrente e al sensore
3. Always combinatorio output: assegna i segnali dei semafori in base allo stato corrente
*/

Smart_traffic_controller/tb_smart_traffic_controller.v
`timescale 1ns/1ps //setting della timescale

module tb_smart_traffic_controller;

    // Segnali di test 
    reg clk; //segnale di clock 
    reg reset_ni; //segnale di reset attivo basso
    reg carB_i; //segnale del sensore  del semaforo B

    //segnale di output
    wire A_red_o; 
    wire A_yellow_o;
    wire A_green_o;
    wire B_red_o;
    wire B_yellow_o;
    wire B_green_o;

    // DUT - inizializzazione dell'istanza del modulo smart_traffic_controller
    smart_traffic_controller DUT (
        .clk_i(clk),
        .reset_ni(reset_ni),
        .carB_i(carB_i),
        .A_red_o(A_red_o),
        .A_yellow_o(A_yellow_o),
        .A_green_o(A_green_o),
        .B_red_o(B_red_o),
        .B_yellow_o(B_yellow_o),
        .B_green_o(B_green_o)
    );

    initial begin
    $dumpfile("sim.vcd");  
    $dumpvars(0, tb_smart_traffic_controller); 
    end
    
    // settiamo il periodo di clock su 10 ns, ogni 5 avviene il cambio fronte
    always #5 clk = ~clk;

    initial begin

        //ogni 5 secondi cambierrà il segnale di clock automaticamente
        // inizializziamo i segnali
        clk      = 0; 
        reset_ni = 0;
        carB_i   = 0;
    
        //aziamo il reset
        #20;
        reset_ni = 1;

        // Attesa delo stato IDLE
        #20;

        // Inviamo il segnale dal semaforo B
        carB_i = 1;
        #10;
        carB_i = 0;

        // simulazione di un ulteriore segnale da ignorare se il circuito è già in funzione
        #20;
        carB_i = 1;
        #10;
        carB_i = 0;

        // Attesa fine sequenza
        #100;

        $finish;
    end

endmodule

Smart_traffic_controller/sim.vcd
$date
	Wed Dec 24 18:35:50 2025
$end
$version
	Icarus Verilog
$end
$timescale
	1ps
$end
$scope module tb_smart_traffic_controller $end
$var wire 1 ! B_yellow_o $end
$var wire 1 " B_red_o $end
$var wire 1 # B_green_o $end
$var wire 1 $ A_yellow_o $end
$var wire 1 % A_red_o $end
$var wire 1 & A_green_o $end
$var reg 1 ' carB_i $end
$var reg 1 ( clk $end
$var reg 1 ) reset_ni $end
$scope module DUT $end
$var wire 1 ' carB_i $end
$var wire 1 ( clk_i $end
$var wire 1 ) reset_ni $end
$var parameter 2 * S_A_YELLOW $end
$var parameter 2 + S_B_GREEN $end
$var parameter 2 , S_B_YELLOW $end
$var parameter 2 - S_IDLE $end
$var reg 1 & A_green_o $end
$var reg 1 % A_red_o $end
$var reg 1 $ A_yellow_o $end
$var reg 1 # B_green_o $end
$var reg 1 " B_red_o $end
$var reg 1 ! B_yellow_o $end
$var reg 2 . cs [1:0] $end
$var reg 2 / next_timer [1:0] $end
$var reg 2 0 ns [1:0] $end
$var reg 2 1 timer [1:0] $end
$upscope $end
$upscope $end
$enddefinitions $end
$comment Show the parameter values. $end
$dumpall
b0 -
b11 ,
b10 +
b1 *
$end
#0
$dumpvars
b0 1
b0 0
b0 /
b0 .
0)
0(
0'
1&
0%
0$
0#
1"
0!
$end
#5000
1(
#10000
0(
#15000
1(
#20000
0(
1)
#25000
1(
#30000
0(
#35000
1(
#40000
b1 0
0(
1'
#45000
1$
1"
0&
b1 /
b1 .
1(
#50000
b1 /
0(
0'
#55000
b0 /
b10 0
b1 1
1(
#60000
0(
#65000
1#
1%
0"
0$
b1 /
b0 1
b10 .
1(
#70000
b1 /
0(
1'
#75000
b10 /
b1 1
1(
#80000
b10 /
0(
0'
#85000
b0 /
b11 0
b10 1
1(
#90000
0(
#95000
1!
0#
1%
b1 /
b0 1
b11 .
1(
#100000
0(
#105000
b0 /
b0 0
b1 1
1(
#110000
0(
#115000
1"
1&
0!
0%
b0 1
b0 .
1(
