Parametric_universal_register/Parametric_universal_register.v
module Parametric_universal_register #(parameter n=8)
(
    input wire clk_i, //clock signal
    input wire reset_ni, //reset signal
    input wire [1:0] mode_i, // 00=hold, 01=shift-left, 10=shift-right, 11=load
    input wire [n-1:0] data_i, //load data input
    input wire ser_i, //input seriale per lo shift
    output reg [n-1:0] data_o //output del registro
);
    reg [n-1:0] data_next;  //reguistro che conterrà il valore successivo
    always @(posedge clk_i or negedge reset_ni) begin  //ad ogni ciclo di clock aggiorniamo il registro
        if (!reset_ni) begin //se il reset è attivo
            data_o <= {n{1'b0}}; // eseguiamo il reset del registro a 0
        end
        else begin
            data_o <= data_next; //aggiorniamo il registro con il valore successivo
        end
    end

    always @(*) begin
        case(mode_i)
            2'b00: data_next = data_o; //hold
            2'b01: data_next = {data_o[n-2:0],ser_i}; //shift-left, il valore più a sinistra viene perso e viene inserito ser_i a destra
            /*[1,0,0,1,1,0,1,1] => [data_o[n-2:0], ser_i] =>
            con ser_i=0 [0,0,1,1,0,1,1,0] (shift a sinistra eseguita)
            */
            2'b10 : data_next = {ser_i, data_o[n-1:1]}; //shift-right, il valore più a destra viene perso e viene inserito ser_i a sinistra
            /*[1,0,0,1,1,0,1,1] => [ser_i, data_o[n-1:1]] =>
            con ser_i=1 [1,1,0,0,1,1,0,1] (shift a destra eseguita)
            */
            2'b11 : data_next = data_i; //load del valore in data_i
            default: data_next = data_o; //default hold
        endcase
    end
endmodule

Parametric_universal_register/tb_pur.v
`timescale 1ns/1ps
module tb_pur; 
    parameter n=8; //larghezza del registro
    reg clk_i; //clock signal
    reg reset_ni; //reset signal
    reg [1:0] mode_i; //00=hold, 01=shift-left, 10=shift-right, 11=load
    reg [n-1:0] data_i; //load data input
    wire [n-1:0] data_o; //output_del registro
    reg ser_i; //input seriale per lo shift

    initial begin
        clk_i = 0;
    end

    Parametric_universal_register #(.n(n)) uut(
        .clk_i(clk_i),
        .reset_ni(reset_ni),
        .mode_i(mode_i),
        .data_i(data_i),
        .ser_i(ser_i),
        .data_o(data_o)
    );

    initial begin
        $dumpfile("tb_pur.vcd"); //nome del file di dump
        $dumpvars(0, tb_pur);  //variabili di dump 
     end

     always #5 clk_i = ~clk_i; //clock con periodo di 10ns, cambio di fronte ogni 5 ns

initial begin
    reset_ni=0;
    mode_i=2'b00;
    data_i=0;
    ser_i=0;
    #2;
    if (data_o !== 0)
        $display("TEST FAILED: reset non funzionante"); //verifica del reset

    reset_ni = 1; //attivazionde del reset
    @(posedge clk_i); //attesa del fronta di salita del clock    
    #1; //ritardo usato per permettere l'aggiornamento dei segnali 
    $display("After reset release, data_o = %b", data_o); 
    //stampiamo il valore di data_o dopo il rilascio del reset

    mode_i = 2'b11; //modalità per il caricamento 
    data_i = 8'b01010101; //valore da caricare 
    @(posedge clk_i); //attesa del clock
    #1; 
    $display("After load, data_o = %b", data_o);

    if (data_o !== 8'b01010101)
        $display("TEST FAILED: load non funzionante");

    mode_i = 2'b00; //modalità hold
    @(posedge clk_i);
    #1;
    $display("After hold, data_o = %b", data_o);

    if (data_o !== 8'b01010101)
        $display("TEST FAILED: hold non funzionante");

    mode_i = 2'b01; //modalità shift-left
    ser_i  = 1'b1;
    @(posedge clk_i);
    #1;
    $display("After shift left, data_o = %b", data_o);

    if (data_o !== 8'b10101011)
        $display("TEST FAILED: shift-left non funzionante");

    mode_i = 2'b10; //modalità shift-right
    ser_i  = 1'b0;
    @(posedge clk_i);
    #1;
    $display("After shift right, data_o = %b", data_o);

    if (data_o !== 8'b01010101)
        $display("TEST FAILED: shift-right non funzionante");

    $display("ALL TESTS PASSED");
    $finish;
end

endmodule

Parametric_universal_register/tb_pur.vcd
$date
	Thu Dec 25 17:39:59 2025
$end
$version
	Icarus Verilog
$end
$timescale
	1ps
$end
$scope module tb_pur $end
$var wire 8 ! data_o [7:0] $end
$var reg 1 " clk_i $end
$var reg 8 # data_i [7:0] $end
$var reg 2 $ mode_i [1:0] $end
$var reg 1 % reset_ni $end
$var reg 1 & ser_i $end
$scope module uut $end
$var wire 1 " clk_i $end
$var wire 8 ' data_i [7:0] $end
$var wire 2 ( mode_i [1:0] $end
$var wire 1 % reset_ni $end
$var wire 1 & ser_i $end
$var reg 8 ) data_next [7:0] $end
$var reg 8 * data_o [7:0] $end
$upscope $end
$upscope $end
$enddefinitions $end
#0
$dumpvars
b0 *
b0 )
b0 (
b0 '
0&
0%
b0 $
b0 #
0"
b0 !
$end
#2000
1%
#5000
1"
#6000
b1010101 )
b1010101 #
b1010101 '
b11 $
b11 (
#10000
0"
#15000
b1010101 !
b1010101 *
1"
#16000
b0 $
b0 (
#20000
0"
#25000
1"
#26000
b10101011 )
1&
b1 $
b1 (
#30000
0"
#35000
b1010111 )
b10101011 !
b10101011 *
1"
#36000
b1010101 )
0&
b10 $
b10 (
#40000
0"
#45000
b101010 )
b1010101 !
b1010101 *
1"
